speculate/__init__.py
speculate-0.0.1.dist-info/METADATA
speculate-0.0.1.dist-info/WHEEL
speculate-0.0.1.dist-info/top_level.txt
speculate-0.0.1.dist-info/RECORD
