Metadata-Version: 2.1
Name: speculate
Version: 0.0.1
Summary: Wouldn't you like to know.
Home-page: https://github.com/interpretml/speculate
Author: interpretml
Author-email: interpretml@microsoft.com
License: UNKNOWN
Platform: UNKNOWN
Classifier: Programming Language :: Python :: 3
Classifier: License :: OSI Approved :: MIT License
Classifier: Operating System :: OS Independent
Requires-Python: >=3.6
